autocron/__init__.py
autocron/admin.py
autocron/configuration.py
autocron/decorators.py
autocron/engine.py
autocron/monitor.py
autocron/schedule.py
autocron/sql_interface.py
autocron/sqlite_interface.py
autocron/worker.py
autocron-1.2.2.dist-info/METADATA
autocron-1.2.2.dist-info/WHEEL
autocron-1.2.2.dist-info/entry_points.txt
autocron-1.2.2.dist-info/top_level.txt
autocron-1.2.2.dist-info/RECORD
