Metadata-Version: 2.1
Name: autocron
Version: 1.2.2
Summary: Asynchronous background tasks for Python web-frameworks with no dependencies
Home-page: https://github.com/kbr/autocron
Author: Klaus Bremer
Author-email: bremer@bremer-media.com
License: MIT
Project-URL: Homepage, https://github.com/kbr/autocron
Project-URL: Code, https://github.com/kbr/autocron
Project-URL: Issue tracker, https://github.com/kbr/autocron/issues
Keywords: tasks,background,python
Platform: any
Classifier: Development Status :: 4 - Beta
Classifier: Intended Audience :: Developers
Classifier: License :: OSI Approved :: MIT License
Classifier: Operating System :: OS Independent
Classifier: Programming Language :: Python
Classifier: Programming Language :: Python :: 3
Classifier: Programming Language :: Python :: 3.8
Classifier: Programming Language :: Python :: 3.9
Classifier: Programming Language :: Python :: 3.10
Classifier: Programming Language :: Python :: 3.11
Classifier: Programming Language :: Python :: 3.12
Classifier: Programming Language :: Python :: 3.13
Classifier: Topic :: Software Development :: Libraries :: Python Modules
Classifier: Topic :: Utilities
